<?xml version="1.0"?>
<!--
/**
 * @category    Oscprofessionals
 * @package     Oscprofessionals_AdvancedNewsletter
 * @author      Oscprofessionals Team <standard@oscprofessionals.com>
 */
-->
<config>
    <modules>
        <Oscprofessionals_AdvancedNewsletter>
            <active>true</active>
            <codePool>community</codePool>
            <priority>1</priority>
            <depends>
                <Mage_Newsletter/>
            </depends>
        </Oscprofessionals_AdvancedNewsletter>
    </modules>
</config>